{
  "images": [
    {
      "id": 1,
      "file_name": "000000486438.jpg",
      "width": 174.93577575683594,
      "height": 97.37622833251953
    },
    {
      "id": 2,
      "file_name": "000000095786.jpg",
      "width": 500,
      "height": 334
    },
    {
      "id": 3,
      "file_name": "000000104612.jpg",
      "width": 640,
      "height": 480
    },
    {
      "id": 4,
      "file_name": "000000096493.jpg",
      "width": 426,
      "height": 640
    },
    {
      "id": 5,
      "file_name": "000000480985.jpg",
      "width": 375,
      "height": 500
    },
    {
      "id": 6,
      "file_name": "000000365387.jpg",
      "width": 640,
      "height": 425
    },
    {
      "id": 7,
      "file_name": "000000252219.jpg",
      "width": 640,
      "height": 428
    },
    {
      "id": 8,
      "file_name": "000000228144.jpg",
      "width": 640,
      "height": 426
    },
    {
      "id": 9,
      "file_name": "000000522713.jpg",
      "width": 640,
      "height": 480
    },
    {
      "id": 10,
      "file_name": "000000456496.jpg",
      "width": 640,
      "height": 426
    }
  ],
  "annotations": [
    {
      "id": 1,
      "image_id": 1,
      "category_id": 55,
      "bbox": [
        251.3794174194336,
        131.86500549316406,
        205.04762268066406,
        111.96304321289062
      ],
      "score": 0.9959911108016968,
      "area": 22957.755838895682,
      "iscrowd": 0
    },
    {
      "id": 2,
      "image_id": 1,
      "category_id": 55,
      "bbox": [
        122.60552978515625,
        120.71566390991211,
        171.49234008789062,
        104.85034942626953
      ],
      "score": 0.9932337999343872,
      "area": 17981.031782143982,
      "iscrowd": 0
    },
    {
      "id": 3,
      "image_id": 1,
      "category_id": 55,
      "bbox": [
        15.970977783203125,
        247.52148056030273,
        216.46791076660156,
        117.42023468017578
      ],
      "score": 0.9929617643356323,
      "area": 25417.712882941705,
      "iscrowd": 0
    },
    {
      "id": 4,
      "image_id": 1,
      "category_id": 55,
      "bbox": [
        354.81842041015625,
        208.53546905517578,
        179.37103271484375,
        110.30009460449219
      ],
      "score": 0.9916582107543945,
      "area": 19784.64187775273,
      "iscrowd": 0
    },
    {
      "id": 5,
      "image_id": 1,
      "category_id": 55,
      "bbox": [
        228.90988159179688,
        259.352725982666,
        227.04217529296875,
        108.68169403076172
      ],
      "score": 0.9901518225669861,
      "area": 24675.328227268998,
      "iscrowd": 0
    },
    {
      "id": 6,
      "image_id": 1,
      "category_id": 55,
      "bbox": [
        -68.55888366699219,
        180.95648193359375,
        196.8014373779297,
        131.1265869140625
      ],
      "score": 0.9829710721969604,
      "area": 25805.900783149526,
      "iscrowd": 0
    },
    {
      "id": 7,
      "image_id": 1,
      "category_id": 55,
      "bbox": [
        -13.19891357421875,
        102.73298263549805,
        174.93577575683594,
        97.37622833251953
      ],
      "score": 0.9812483787536621,
      "area": 17034.58604362409,
      "iscrowd": 0
    },
    {
      "id": 8,
      "image_id": 2,
      "category_id": 42,
      "bbox": [
        80.20551204681396,
        -92.90772080421448,
        242.6535129547119,
        186.5492343902588
      ],
      "score": 0.917165994644165,
      "area": 74165.16946134344,
      "iscrowd": 0
    },
    {
      "id": 9,
      "image_id": 2,
      "category_id": 42,
      "bbox": [
        -103.8527250289917,
        -93.8563346862793,
        211.57419681549072,
        257.1220874786377
      ],
      "score": 0.8942595720291138,
      "area": 89129.61395394988,
      "iscrowd": 0
    },
    {
      "id": 10,
      "image_id": 2,
      "category_id": 42,
      "bbox": [
        119.06900405883789,
        80.0790786743164,
        226.13153457641602,
        167.23735332489014
      ],
      "score": 0.8912323713302612,
      "area": 61960.42030424997,
      "iscrowd": 0
    },
    {
      "id": 11,
      "image_id": 4,
      "category_id": 1,
      "bbox": [
        -221.91610717773438,
        -323.1995544433594,
        430.5190734863281,
        627.0595703125
      ],
      "score": 0.6955074071884155,
      "area": 269961.1052316725,
      "iscrowd": 0
    },
    {
      "id": 12,
      "image_id": 4,
      "category_id": 60,
      "bbox": [
        -219.87460327148438,
        -288.8543701171875,
        431.78387451171875,
        621.8677978515625
      ],
      "score": 0.5980244874954224,
      "area": 268512.48719041795,
      "iscrowd": 0
    },
    {
      "id": 13,
      "image_id": 4,
      "category_id": 66,
      "bbox": [
        46.515899658203125,
        328.44556427001953,
        121.09886169433594,
        40.54899597167969
      ],
      "score": 0.6403681635856628,
      "area": 4910.437255018624,
      "iscrowd": 0
    },
    {
      "id": 14,
      "image_id": 4,
      "category_id": 74,
      "bbox": [
        52.90585708618164,
        329.5550289154053,
        114.32769012451172,
        40.46171951293945
      ],
      "score": 0.7179975509643555,
      "area": 4625.894930380251,
      "iscrowd": 0
    },
    {
      "id": 15,
      "image_id": 5,
      "category_id": 1,
      "bbox": [
        37.09896802902222,
        277.7125209569931,
        23.19074273109436,
        35.53555607795715
      ],
      "score": 0.9982191324234009,
      "area": 1350.1987861467642,
      "iscrowd": 0
    },
    {
      "id": 16,
      "image_id": 5,
      "category_id": 1,
      "bbox": [
        22.46040776371956,
        284.0793162584305,
        17.83153861761093,
        30.227988958358765
      ],
      "score": 0.9945180416107178,
      "area": 883.1165275237436,
      "iscrowd": 0
    },
    {
      "id": 17,
      "image_id": 5,
      "category_id": 1,
      "bbox": [
        306.3804894685745,
        223.9638090133667,
        27.310222387313843,
        105.36389350891113
      ],
      "score": 0.9935227632522583,
      "area": 4714.5146176661365,
      "iscrowd": 0
    },
    {
      "id": 18,
      "image_id": 5,
      "category_id": 1,
      "bbox": [
        256.635557115078,
        243.63014996051788,
        23.49388897418976,
        94.08792853355408
      ],
      "score": 0.944701075553894,
      "area": 3621.669022562419,
      "iscrowd": 0
    },
    {
      "id": 19,
      "image_id": 5,
      "category_id": 4,
      "bbox": [
        270.62543481588364,
        293.1901276111603,
        39.337947964668274,
        47.56888151168823
      ],
      "score": 0.7958889007568359,
      "area": 3065.8759649595595,
      "iscrowd": 0
    },
    {
      "id": 20,
      "image_id": 6,
      "category_id": 62,
      "bbox": [
        29.788238525390625,
        140.56580352783203,
        166.2676544189453,
        160.4622039794922
      ],
      "score": 0.9981719851493835,
      "area": 26679.67427856452,
      "iscrowd": 0
    },
    {
      "id": 21,
      "image_id": 7,
      "category_id": 1,
      "bbox": [
        290.2354164123535,
        69.15665435791016,
        71.70769500732422,
        201.76036071777344
      ],
      "score": 0.9996720552444458,
      "area": 14467.770410917816,
      "iscrowd": 0
    },
    {
      "id": 22,
      "image_id": 7,
      "category_id": 1,
      "bbox": [
        -58.607460021972656,
        52.519500732421875,
        126.75279998779297,
        228.81838989257812
      ],
      "score": 0.9992421865463257,
      "area": 29003.371607582783,
      "iscrowd": 0
    },
    {
      "id": 23,
      "image_id": 7,
      "category_id": 1,
      "bbox": [
        443.69549560546875,
        65.34585571289062,
        126.06890869140625,
        213.55703735351562
      ],
      "score": 0.9970448017120361,
      "area": 26922.902642527595,
      "iscrowd": 0
    },
    {
      "id": 24,
      "image_id": 7,
      "category_id": 10,
      "bbox": [
        309.40549659729004,
        13.447662353515625,
        59.70670700073242,
        61.879066467285156
      ],
      "score": 0.9985897541046143,
      "area": 3694.5952910410415,
      "iscrowd": 0
    },
    {
      "id": 25,
      "image_id": 7,
      "category_id": 26,
      "bbox": [
        521.8097534179688,
        53.95848846435547,
        77.5899658203125,
        68.00698852539062
      ],
      "score": 0.9941332340240479,
      "area": 5276.659915227443,
      "iscrowd": 0
    },
    {
      "id": 26,
      "image_id": 8,
      "category_id": 57,
      "bbox": [
        -107.12307739257812,
        -70.84027099609375,
        214.07220458984375,
        326.522705078125
      ],
      "score": 0.969662070274353,
      "area": 69899.43532471359,
      "iscrowd": 0
    },
    {
      "id": 27,
      "image_id": 8,
      "category_id": 58,
      "bbox": [
        229.26730346679688,
        126.33600234985352,
        145.83734130859375,
        108.15245819091797
      ],
      "score": 0.7416878938674927,
      "area": 15772.66695855232,
      "iscrowd": 0
    },
    {
      "id": 28,
      "image_id": 8,
      "category_id": 59,
      "bbox": [
        -34.671939849853516,
        58.07536315917969,
        69.99382781982422,
        75.74716186523438
      ],
      "score": 0.997026801109314,
      "area": 5301.83380543557,
      "iscrowd": 0
    },
    {
      "id": 29,
      "image_id": 9,
      "category_id": 9,
      "bbox": [
        426.14506244659424,
        259.12183904647827,
        26.321874618530273,
        8.649632453918457
      ],
      "score": 0.9987185001373291,
      "area": 227.67454094841196,
      "iscrowd": 0
    },
    {
      "id": 30,
      "image_id": 9,
      "category_id": 14,
      "bbox": [
        329.95996856689453,
        246.99643325805664,
        155.03099060058594,
        73.11913299560547
      ],
      "score": 0.9853975176811218,
      "area": 11335.731620164705,
      "iscrowd": 0
    },
    {
      "id": 31,
      "image_id": 10,
      "category_id": 1,
      "bbox": [
        79.74373626708984,
        -54.071197509765625,
        144.87513732910156,
        239.81646728515625
      ],
      "score": 0.9963270425796509,
      "area": 34743.443631717004,
      "iscrowd": 0
    },
    {
      "id": 32,
      "image_id": 10,
      "category_id": 15,
      "bbox": [
        92.01085090637207,
        255.94412422180176,
        59.54478073120117,
        60.021663665771484
      ],
      "score": 0.9990553855895996,
      "area": 3573.9768021002674,
      "iscrowd": 0
    },
    {
      "id": 33,
      "image_id": 10,
      "category_id": 15,
      "bbox": [
        264.99940299987793,
        311.4129276275635,
        20.36221694946289,
        27.657970428466797
      ],
      "score": 0.998022735118866,
      "area": 563.17759424627,
      "iscrowd": 0
    },
    {
      "id": 34,
      "image_id": 10,
      "category_id": 15,
      "bbox": [
        -12.96219253540039,
        275.9524517059326,
        69.46561431884766,
        40.742801666259766
      ],
      "score": 0.9978804588317871,
      "area": 2830.2237468177045,
      "iscrowd": 0
    },
    {
      "id": 35,
      "image_id": 10,
      "category_id": 15,
      "bbox": [
        353.1131796836853,
        312.53610706329346,
        12.457966804504395,
        20.496084213256836
      ],
      "score": 0.9958879947662354,
      "area": 255.33953675108023,
      "iscrowd": 0
    },
    {
      "id": 36,
      "image_id": 10,
      "category_id": 15,
      "bbox": [
        385.5086250305176,
        299.0598030090332,
        34.460350036621094,
        65.6473617553711
      ],
      "score": 0.9721494913101196,
      "area": 2262.2310650707805,
      "iscrowd": 0
    }
  ],
  "categories": [
    {
      "id": 1,
      "name": "person"
    },
    {
      "id": 2,
      "name": "bicycle"
    },
    {
      "id": 3,
      "name": "car"
    },
    {
      "id": 4,
      "name": "motorcycle"
    },
    {
      "id": 5,
      "name": "airplane"
    },
    {
      "id": 6,
      "name": "bus"
    },
    {
      "id": 7,
      "name": "train"
    },
    {
      "id": 8,
      "name": "truck"
    },
    {
      "id": 9,
      "name": "boat"
    },
    {
      "id": 10,
      "name": "traffic_light"
    },
    {
      "id": 11,
      "name": "fire_hydrant"
    },
    {
      "id": 12,
      "name": "stop_sign"
    },
    {
      "id": 13,
      "name": "parking_meter"
    },
    {
      "id": 14,
      "name": "bench"
    },
    {
      "id": 15,
      "name": "bird"
    },
    {
      "id": 16,
      "name": "cat"
    },
    {
      "id": 17,
      "name": "dog"
    },
    {
      "id": 18,
      "name": "horse"
    },
    {
      "id": 19,
      "name": "sheep"
    },
    {
      "id": 20,
      "name": "cow"
    },
    {
      "id": 21,
      "name": "elephant"
    },
    {
      "id": 22,
      "name": "bear"
    },
    {
      "id": 23,
      "name": "zebra"
    },
    {
      "id": 24,
      "name": "giraffe"
    },
    {
      "id": 25,
      "name": "backpack"
    },
    {
      "id": 26,
      "name": "umbrella"
    },
    {
      "id": 27,
      "name": "handbag"
    },
    {
      "id": 28,
      "name": "tie"
    },
    {
      "id": 29,
      "name": "suitcase"
    },
    {
      "id": 30,
      "name": "frisbee"
    },
    {
      "id": 31,
      "name": "skis"
    },
    {
      "id": 32,
      "name": "snowboard"
    },
    {
      "id": 33,
      "name": "sports_ball"
    },
    {
      "id": 34,
      "name": "kite"
    },
    {
      "id": 35,
      "name": "baseball_bat"
    },
    {
      "id": 36,
      "name": "baseball_glove"
    },
    {
      "id": 37,
      "name": "skateboard"
    },
    {
      "id": 38,
      "name": "surfboard"
    },
    {
      "id": 39,
      "name": "tennis_racket"
    },
    {
      "id": 40,
      "name": "bottle"
    },
    {
      "id": 41,
      "name": "wine_glass"
    },
    {
      "id": 42,
      "name": "cup"
    },
    {
      "id": 43,
      "name": "fork"
    },
    {
      "id": 44,
      "name": "knife"
    },
    {
      "id": 45,
      "name": "spoon"
    },
    {
      "id": 46,
      "name": "bowl"
    },
    {
      "id": 47,
      "name": "banana"
    },
    {
      "id": 48,
      "name": "apple"
    },
    {
      "id": 49,
      "name": "sandwich"
    },
    {
      "id": 50,
      "name": "orange"
    },
    {
      "id": 51,
      "name": "broccoli"
    },
    {
      "id": 52,
      "name": "carrot"
    },
    {
      "id": 53,
      "name": "hot_dog"
    },
    {
      "id": 54,
      "name": "pizza"
    },
    {
      "id": 55,
      "name": "donut"
    },
    {
      "id": 56,
      "name": "cake"
    },
    {
      "id": 57,
      "name": "chair"
    },
    {
      "id": 58,
      "name": "couch"
    },
    {
      "id": 59,
      "name": "potted_plant"
    },
    {
      "id": 60,
      "name": "bed"
    },
    {
      "id": 61,
      "name": "dining_table"
    },
    {
      "id": 62,
      "name": "toilet"
    },
    {
      "id": 63,
      "name": "tv"
    },
    {
      "id": 64,
      "name": "laptop"
    },
    {
      "id": 65,
      "name": "mouse"
    },
    {
      "id": 66,
      "name": "remote"
    },
    {
      "id": 67,
      "name": "keyboard"
    },
    {
      "id": 68,
      "name": "cell_phone"
    },
    {
      "id": 69,
      "name": "microwave"
    },
    {
      "id": 70,
      "name": "oven"
    },
    {
      "id": 71,
      "name": "toaster"
    },
    {
      "id": 72,
      "name": "sink"
    },
    {
      "id": 73,
      "name": "refrigerator"
    },
    {
      "id": 74,
      "name": "book"
    },
    {
      "id": 75,
      "name": "clock"
    },
    {
      "id": 76,
      "name": "vase"
    },
    {
      "id": 77,
      "name": "scissors"
    },
    {
      "id": 78,
      "name": "teddy_bear"
    },
    {
      "id": 79,
      "name": "hair_drier"
    },
    {
      "id": 80,
      "name": "toothbrush"
    }
  ]
}